mmragsdk/__init__.py
mmragsdk/client.py
mmragsdk/_requests/__init__.py
mmragsdk/_requests/factory.py
mmragsdk/_requests/models.py
mmragsdk-1.0.8.dist-info/METADATA
mmragsdk-1.0.8.dist-info/WHEEL
mmragsdk-1.0.8.dist-info/licenses/LICENSE
mmragsdk-1.0.8.dist-info/RECORD
